cpnet/BE.py
cpnet/CPAlgorithm.py
cpnet/Cucuringu.py
cpnet/Divisive.py
cpnet/KM_ER.py
cpnet/KM_config.py
cpnet/Lip.py
cpnet/MINRES.py
cpnet/Rombach.py
cpnet/Rossa.py
cpnet/Surprise.py
cpnet/__init__.py
cpnet/adam.py
cpnet/qstest.py
cpnet/utils.py
cpnet-0.0.20.dist-info/LICENSE
cpnet-0.0.20.dist-info/METADATA
cpnet-0.0.20.dist-info/WHEEL
cpnet-0.0.20.dist-info/top_level.txt
cpnet-0.0.20.dist-info/RECORD
